MANIFEST.in
README.rst
buildout.cfg
develop.cfg
requirements.txt
setup.py
version.txt
bob/__init__.py
bob.db.voicepa.egg-info/PKG-INFO
bob.db.voicepa.egg-info/SOURCES.txt
bob.db.voicepa.egg-info/dependency_links.txt
bob.db.voicepa.egg-info/entry_points.txt
bob.db.voicepa.egg-info/not-zip-safe
bob.db.voicepa.egg-info/requires.txt
bob.db.voicepa.egg-info/top_level.txt
bob/db/__init__.py
bob/db/voicepa/__init__.py
bob/db/voicepa/checkfiles.py
bob/db/voicepa/create.py
bob/db/voicepa/driver.py
bob/db/voicepa/dumplist.py
bob/db/voicepa/models.py
bob/db/voicepa/protocols.tar.gz
bob/db/voicepa/query.py
bob/db/voicepa/test.py
doc/conf.py
doc/guide.rst
doc/index.rst
doc/py_api.rst